odoo8_addon_sale_commission_formula-8.0.1.0.0.99.dev26-py3.8-nspkg.pth
odoo_addons/sale_commission_formula/README.rst
odoo_addons/sale_commission_formula/__init__.py
odoo_addons/sale_commission_formula/__openerp__.py
odoo_addons/sale_commission_formula/demo/commission_demo.xml
odoo_addons/sale_commission_formula/i18n/ca.po
odoo_addons/sale_commission_formula/i18n/da_DK.po
odoo_addons/sale_commission_formula/i18n/de.po
odoo_addons/sale_commission_formula/i18n/el_GR.po
odoo_addons/sale_commission_formula/i18n/es.po
odoo_addons/sale_commission_formula/i18n/fi.po
odoo_addons/sale_commission_formula/i18n/fr.po
odoo_addons/sale_commission_formula/i18n/gl.po
odoo_addons/sale_commission_formula/i18n/it.po
odoo_addons/sale_commission_formula/i18n/pt.po
odoo_addons/sale_commission_formula/i18n/pt_BR.po
odoo_addons/sale_commission_formula/i18n/pt_PT.po
odoo_addons/sale_commission_formula/i18n/ro.po
odoo_addons/sale_commission_formula/i18n/ru.po
odoo_addons/sale_commission_formula/i18n/sale_commission_formula.pot
odoo_addons/sale_commission_formula/i18n/sl.po
odoo_addons/sale_commission_formula/i18n/tr.po
odoo_addons/sale_commission_formula/i18n/tr_TR.po
odoo_addons/sale_commission_formula/i18n/zh_CN.po
odoo_addons/sale_commission_formula/models/__init__.py
odoo_addons/sale_commission_formula/models/account_invoice.py
odoo_addons/sale_commission_formula/models/sale_commission.py
odoo_addons/sale_commission_formula/models/sale_order.py
odoo_addons/sale_commission_formula/static/description/icon.png
odoo_addons/sale_commission_formula/static/description/icon.svg
odoo_addons/sale_commission_formula/static/src/css/sale_commission_formula.css
odoo_addons/sale_commission_formula/tests/__init__.py
odoo_addons/sale_commission_formula/tests/test_commission_formula.py
odoo_addons/sale_commission_formula/views/sale_commission_view.xml
odoo8_addon_sale_commission_formula-8.0.1.0.0.99.dev26.dist-info/METADATA
odoo8_addon_sale_commission_formula-8.0.1.0.0.99.dev26.dist-info/WHEEL
odoo8_addon_sale_commission_formula-8.0.1.0.0.99.dev26.dist-info/namespace_packages.txt
odoo8_addon_sale_commission_formula-8.0.1.0.0.99.dev26.dist-info/top_level.txt
odoo8_addon_sale_commission_formula-8.0.1.0.0.99.dev26.dist-info/RECORD
